_jack.py
jack.py
JACK_Client-0.5.5.dist-info/LICENSE
JACK_Client-0.5.5.dist-info/METADATA
JACK_Client-0.5.5.dist-info/WHEEL
JACK_Client-0.5.5.dist-info/top_level.txt
JACK_Client-0.5.5.dist-info/zip-safe
JACK_Client-0.5.5.dist-info/RECORD
